


[

{
    "name": "onepiece",
    "img": "https://static.bunnycdn.ru/i/cache/images/4/42/422670a855efae8d8d8fafb59d43c197.jpg",
    "year": "1999",
    "genre": ["Action"],
    "rating": "9.2",
    "link":"https://zoroanime.co/watch/one-piece.ov8/ep-1"
},
{
    "name": "Chainsaw man",
    "img": "https://static.bunnycdn.ru/i/cache/images/9/9e/9e12905bf8156dba240756891e906f68.jpg",
    "year": "2022",
    "genre": ["Drama","Crime"],
    "rating": "9.2",
    "link":"https://zoroanime.co/watch/chainsaw-man.8o9q/ep-1"
},
{
    "name": "Mob Psycho 100",
    "img": "https://static.bunnycdn.ru/i/cache/images/8/89/89c3cbdac91356f5b8e5898013470846.jpg",
    "year": "2022",
    "genre": ["Action", "Adventure"],
    "rating": "9.0",
    "link":"https://zoroanime.co/watch/mob-psycho-100-iii.yqqv0/ep-1"
},
{
    "name": "SPY x FAMILY",
    "img": "https://static.bunnycdn.ru/i/cache/images/4/4e/4e439e9a2859ba3a77723c72fa08c339.jpg",
    "year": "2022",
    "genre": ["Drama","Crime"],
    "rating": "8.9",
    "link":"https://zoroanime.co/watch/spy-x-family-part-2.vvvo6/ep-1"
},
{
    "name": "My hero academia",
    "img": "https://static.bunnycdn.ru/i/cache/images/3/3b/3ba8e07776041325e2a67856465546e5.jpg",
    "year": "2022",
    "genre": ["Drama","Romance"],
    "rating": "8.8",
    "link":"https://zoroanime.co/watch/boku-no-hero-academia-6.xrrvz/ep-1"
},
{
    "name": "The Daily Life of the Immortal King",
    "img": "https://static.bunnycdn.ru/i/cache/images/b/b6/b64fd34692e1dde03f0eb4a35289eeb5.jpg",
    "year": "2022",
    "genre": ["Drama","Thriller"],
    "rating": "8.8",
    "link":"https://zoroanime.co/watch/the-daily-life-of-the-immortal-king-3.prr5x/ep-1"
},
{
    "name": "Dr. stone",
    "img": "https://static.bunnycdn.ru/i/cache/images/b/b6/b64fd34692e1dde03f0eb4a35289eeb5.jpg",
    "year": "2019",
    "genre": ["Sci-fi", "Action"],
    "rating": "8.7",
    "link":"https://zoroanime.co/watch/dr-stone.lo6q/ep-1"
},
{
    "name": "Saga of Tanya the Evil: War Report",
    "img": "https://static.bunnycdn.ru/i/cache/images/0/0f/0f8c29031c3c2e012440946038218b2e.jpg",
    "year": "2017",
    "genre": ["Drama","Crime"],
    "rating": "8.7",
    "link":"https://zoroanime.co/watch/youjo-senki-senkyou-houkoku.340y/ep-full"
},
{
    "name": "Akame ga Kill!",
    "img": "https://static.bunnycdn.ru/i/cache/images/2018/04/81ec495b45d2bd4b385249142c4e2878.jpg",
    "year": "2014",
    "genre": ["Sci-fi", "Adventure"],
    "rating": "8.6",
    "link":"https://zoroanime.co/watch/akame-ga-kill.908/ep-1"
},
{
    "name": "Overlord",
    "img": "https://static.bunnycdn.ru/i/cache/images/2018/04/eb9e6b6cf43ecbe7431003553ab99195.jpg",
    "year": "2015",
    "genre": ["Drama", "Music"],
    "rating": "8.5",
    "link":"https://zoroanime.co/watch/overlord.o35/ep-1"
},
{
    "name": "The Eminence in Shadow",
    "img": "https://static.bunnycdn.ru/i/cache/images/b/b4/b4b8f02a8ca80bac7f7806cde7703e12.jpg",
    "year": "2022",
    "genre": ["Thriller", "Drama"],
    "rating": "8.5",
    "link":"https://zoroanime.co/watch/the-eminence-in-shadow.4ylx/ep-1"
},
{
    "name": "Welcome to Demon School! Iruma-kun",
    "img": "https://static.bunnycdn.ru/i/cache/images/e/ee/ee42f858c8b13d7fb4682755d557c60e.jpg",
    "year": "2022",
    "genre": ["Family", "Action"],
    "rating": "8.3",
    "link":"https://zoroanime.co/watch/welcome-to-demon-school-iruma-kun-season-3.vvnw7/ep-1"
},
{
    "name": "https://zoroanime.co/watch/akiba-maid-war.ojxq8/ep-1",
    "img": "https://static.bunnycdn.ru/i/cache/images/7/73/7373e588b9c6c48faec627da79c278ba.jpg",
    "year": "2022",
    "genre": ["Family", "Adventure"],
    "rating": "8.3",
    "link":"https://zoroanime.co/watch/akiba-maid-war.ojxq8/ep-1"
},
{
    "name": "Sexy",
    "img": "https://static.bunnycdn.ru/i/cache/images/a/ab/ab4f283bdfac41b1f7d81987cfb4b120.jpg",
    "year": "2016",
    "genre": ["Romance", "Sexy"],
    "rating": "8.3",
    "link":"https://zoroanime.co/watch/dokyuu-hentai-hxeros-hxeros-report.2rl4/ep-full"
}
] 





